{
  "display": {
    "icon": {
      "id": "the_divine_engine:industrialfurnance"
    },
    "title": {
      "translate": "advancements.rawblastfurnanceadvancement.title"
    },
    "description": {
      "translate": "advancements.rawblastfurnanceadvancement.descr"
    },
    "frame": "task",
    "show_toast": true,
    "announce_to_chat": true,
    "hidden": false
  },
  "criteria": {
    "rawblastfurnanceadvancement_0": {
      "trigger": "minecraft:inventory_changed",
      "conditions": {
        "items": [
          {
            "items": [
              "the_divine_engine:industrialfurnance"
            ],
            "count": {
              "min": 1,
              "max": 64
            }
          }
        ]
      }
    }
  },
  "parent": "the_divine_engine:beginadvancement"
}